<?xml version="1.0" encoding="UTF-8" standalone="yes"?>
<ServersConfig xmlns:ns2="http://www.armangal.com/smartexecutormonitor/v1">
	<name>Perf Monitoring</name>
	<username>admin</username>
	<password>password</password>
	<servers>
		<server>
			<name>channel1</name>
			<serverCode>3170</serverCode>
			<ip>172.31.157.70</ip>
			<jmxPort>10001</jmxPort>
			<authenticate>false</authenticate>
			<username>admin</username>
			<password>password</password>
		</server>
		<server>
			<name>channel2</name>
			<serverCode>3171</serverCode>
			<ip>172.31.157.70</ip>
			<jmxPort>10002</jmxPort>
			<authenticate>false</authenticate>
			<username>admin</username>
			<password>password</password>
		</server>
		<!-- -->
		<server>
			<name>channel3</name>
			<serverCode>3172</serverCode>
			<ip>172.31.157.71</ip>
			<jmxPort>10003</jmxPort>
			<authenticate>false</authenticate>
			<username>admin</username>
			<password>password</password>
		</server>
		<server>
			<name>channel4</name>
			<serverCode>3173</serverCode>
			<ip>172.31.157.71</ip>
			<jmxPort>10004</jmxPort>
			<authenticate>false</authenticate>
			<username>admin</username>
			<password>password</password>
		</server>
		<!-- -->
		<server>
			<name>channel5</name>
			<serverCode>3174</serverCode>
			<ip>172.31.157.72</ip>
			<jmxPort>10005</jmxPort>
			<authenticate>false</authenticate>
			<username>admin</username>
			<password>password</password>
		</server>
		<server>
			<name>channel6</name>
			<serverCode>3175</serverCode>
			<ip>172.31.157.72</ip>
			<jmxPort>10006</jmxPort>
			<authenticate>false</authenticate>
			<username>admin</username>
			<password>password</password>
		</server>
		<!-- -->
		<server>
			<name>channel7</name>
			<serverCode>3176</serverCode>
			<ip>172.31.157.73</ip>
			<jmxPort>10007</jmxPort>
			<authenticate>false</authenticate>
			<username>admin</username>
			<password>password</password>
		</server>
		<server>
			<name>channel8</name>
			<serverCode>3177</serverCode>
			<ip>172.31.157.73</ip>
			<jmxPort>10008</jmxPort>
			<authenticate>false</authenticate>
			<username>admin</username>
			<password>password</password>
		</server>
		<!-- -->
		<server>
			<name>channel9</name>
			<serverCode>3178</serverCode>
			<ip>172.31.157.74</ip>
			<jmxPort>10009</jmxPort>
			<authenticate>false</authenticate>
			<username>admin</username>
			<password>password</password>
		</server>
		<server>
			<name>channel10</name>
			<serverCode>3179</serverCode>
			<ip>172.31.157.74</ip>
			<jmxPort>10010</jmxPort>
			<authenticate>false</authenticate>
			<username>admin</username>
			<password>password</password>
		</server>
		<!-- -->
		<server>
			<name>channel11</name>
			<serverCode>3180</serverCode>
			<ip>172.31.157.75</ip>
			<jmxPort>10011</jmxPort>
			<authenticate>false</authenticate>
			<username>admin</username>
			<password>password</password>
		</server>
		<server>
			<name>channel12</name>
			<serverCode>3181</serverCode>
			<ip>172.31.157.75</ip>
			<jmxPort>10012</jmxPort>
			<authenticate>false</authenticate>
			<username>admin</username>
			<password>password</password>
		</server>

		<!-- -->
		<server>
			<name>channel13</name>
			<serverCode>3182</serverCode>
			<ip>172.31.157.76</ip>
			<jmxPort>10013</jmxPort>
			<authenticate>false</authenticate>
			<username>admin</username>
			<password>password</password>
		</server>
		<server>
			<name>channel14</name>
			<serverCode>3183</serverCode>
			<ip>172.31.157.76</ip>
			<jmxPort>10014</jmxPort>
			<authenticate>false</authenticate>
			<username>admin</username>
			<password>password</password>
		</server>

		<!-- -->
		<server>
			<name>channel15</name>
			<serverCode>3184</serverCode>
			<ip>172.31.157.77</ip>
			<jmxPort>10015</jmxPort>
			<authenticate>false</authenticate>
			<username>admin</username>
			<password>password</password>
		</server>
		<server>
			<name>channel16</name>
			<serverCode>3185</serverCode>
			<ip>172.31.157.77</ip>
			<jmxPort>10016</jmxPort>
			<authenticate>false</authenticate>
			<username>admin</username>
			<password>password</password>
		</server>

		<!-- -->
		<server>
			<name>channel17</name>
			<serverCode>3186</serverCode>
			<ip>172.31.157.78</ip>
			<jmxPort>10017</jmxPort>
			<authenticate>false</authenticate>
			<username>admin</username>
			<password>password</password>
		</server>
		<server>
			<name>channel18</name>
			<serverCode>3187</serverCode>
			<ip>172.31.157.78</ip>
			<jmxPort>10018</jmxPort>
			<authenticate>false</authenticate>
			<username>admin</username>
			<password>password</password>
		</server>

		<!-- -->
		<server>
			<name>channel19</name>
			<serverCode>3188</serverCode>
			<ip>172.31.157.79</ip>
			<jmxPort>10019</jmxPort>
			<authenticate>false</authenticate>
			<username>admin</username>
			<password>password</password>
		</server>
		<server>
			<name>channel20</name>
			<serverCode>3189</serverCode>
			<ip>172.31.157.79</ip>
			<jmxPort>10020</jmxPort>
			<authenticate>false</authenticate>
			<username>admin</username>
			<password>password</password>
		</server>

		<!-- -->
		<server>
			<name>channel21</name>
			<serverCode>3190</serverCode>
			<ip>172.31.157.80</ip>
			<jmxPort>10021</jmxPort>
			<authenticate>false</authenticate>
			<username>admin</username>
			<password>password</password>
		</server>
		<server>
			<name>channel22</name>
			<serverCode>3365</serverCode>
			<ip>172.31.157.80</ip>
			<jmxPort>10022</jmxPort>
			<authenticate>false</authenticate>
			<username>admin</username>
			<password>password</password>
		</server>

		<!-- -->
		<server>
			<name>channel23</name>
			<serverCode>3366</serverCode>
			<ip>172.31.157.81</ip>
			<jmxPort>10023</jmxPort>
			<authenticate>false</authenticate>
			<username>admin</username>
			<password>password</password>
		</server>
		<server>
			<name>channel24</name>
			<serverCode>3367</serverCode>
			<ip>172.31.157.81</ip>
			<jmxPort>10024</jmxPort>
			<authenticate>false</authenticate>
			<username>admin</username>
			<password>password</password>
		</server>

		<server>
			<name>Local (1)</name>
			<serverCode>15</serverCode>
			<ip>127.0.0.1</ip>
			<jmxPort>9010</jmxPort>
			<authenticate>true</authenticate>
			<username>admin</username>
			<password>password</password>
		</server>

		<server>
			<name>EDI_CHANNEL</name>
			<serverCode>17</serverCode>
			<ip>192.168.203.110</ip>
			<jmxPort>9010</jmxPort>
			<authenticate>false</authenticate>
			<username>user</username>
			<password>password</password>
		</server>

		<server>
			<name>EDI_LOBBY</name>
			<serverCode>18</serverCode>
			<ip>192.168.203.110</ip>
			<jmxPort>9020</jmxPort>
			<authenticate>false</authenticate>
			<username>user</username>
			<password>password</password>
		</server>
		<server>
			<name>EDI_GAME</name>
			<serverCode>19</serverCode>
			<ip>192.168.203.110</ip>
			<jmxPort>9030</jmxPort>
			<authenticate>false</authenticate>
			<username>user</username>
			<password>password</password>
		</server>
	</servers>
</ServersConfig>